reshaper.py
reshaper-1.1.1.dist-info/METADATA
reshaper-1.1.1.dist-info/WHEEL
reshaper-1.1.1.dist-info/entry_points.txt
reshaper-1.1.1.dist-info/top_level.txt
reshaper-1.1.1.dist-info/RECORD
