Metadata-Version: 2.1
Name: reshaper
Version: 1.1.1
Summary: # Reshaper
Home-page: https://github.com/sanand0/reshaper
Author: S Anand
Author-email: root.node@gmail.com
License: MIT
Keywords: reshaper
Classifier: Development Status :: 4 - Beta
Classifier: Intended Audience :: Developers
Classifier: License :: Other/Proprietary License
Classifier: Natural Language :: English
Classifier: Programming Language :: Python :: 2
Classifier: Programming Language :: Python :: 2.7
Classifier: Programming Language :: Python :: 3
Classifier: Programming Language :: Python :: 3.6
Requires-Dist: pandas
Requires-Dist: scipy
Requires-Dist: tqdm
Requires-Dist: GDAL
